checkgen/__init__.py
checkgen/document.py
checkgen/models.py
checkgen/printer.py
checkgen/assets/fonts/Cookie-Regular.ttf
checkgen/assets/fonts/OpenSans-Regular.ttf
checkgen/assets/fonts/TitilliumWeb-Regular.ttf
checkgen/assets/fonts/micrenc.ttf
checkgen-0.3.2.dist-info/METADATA
checkgen-0.3.2.dist-info/WHEEL
checkgen-0.3.2.dist-info/licenses/LICENSE
checkgen-0.3.2.dist-info/RECORD
