Metadata-Version: 2.3
Name: checkgen
Version: 0.3.2
Summary: Print bank checks
Project-URL: Homepage, https://github.com/yankyhoffman/check-generator
Author: Yanky Hoffman
License-File: LICENSE
Classifier: License :: OSI Approved :: MIT License
Classifier: Operating System :: OS Independent
Classifier: Programming Language :: Python :: 3
Requires-Python: >=3.7
Requires-Dist: fpdf2==2.7.9
Requires-Dist: num2words==0.5.13
